AUTHORS.md
LICENSE
MANIFEST.in
README.md
setup.py
wad/__init__.py
wad/__main__.py
wad/clues.py
wad/detection.py
wad/group.py
wad/output.py
wad/tools.py
wad.egg-info/PKG-INFO
wad.egg-info/SOURCES.txt
wad.egg-info/dependency_links.txt
wad.egg-info/entry_points.txt
wad.egg-info/top_level.txt
wad/etc/README.md
wad/etc/apps.json
wad/etc/apps.json.other
wad/tests/__init__.py
wad/tests/test_clues.py
wad/tests/test_detection.py
wad/tests/test_group.py
wad/tests/test_output.py
wad/tests/data/__init__.py
wad/tests/data/data_test_wad.py